README.md
setup.cfg
setup.py
nzbclients/__init__.py
nzbclients.egg-info/PKG-INFO
nzbclients.egg-info/SOURCES.txt
nzbclients.egg-info/dependency_links.txt
nzbclients.egg-info/requires.txt
nzbclients.egg-info/top_level.txt
nzbclients/nzbdrone/__init__.py
nzbclients/nzbdrone/common.py
nzbclients/nzbdrone/exceptions.py
nzbclients/nzbdrone/rest_client.py
nzbclients/nzbdrone/radarr/__init__.py
nzbclients/nzbdrone/radarr/client.py
nzbclients/nzbdrone/radarr/domain/__init__.py
nzbclients/nzbdrone/radarr/domain/movie.py
nzbclients/nzbdrone/sonarr/__init__.py
nzbclients/nzbdrone/sonarr/client.py
nzbclients/nzbdrone/sonarr/domain/__init__.py
nzbclients/nzbdrone/sonarr/domain/episode.py
nzbclients/nzbdrone/sonarr/domain/profile.py
nzbclients/nzbdrone/sonarr/domain/series.py