Metadata-Version: 1.1
Name: nzbclients
Version: 0.1.3
Summary: A library of unofficial library of clients for interacting with programs that download NZB files.
Home-page: https://github.com/jblakeney/nzbclients
Author: Jeff Blakeney
Author-email: jblakeneypypi@gmail.com
License: MIT
Keywords: radarr,sabnzbd,sonarr,nzbdrone,nzb
Platform: UNKNOWN
Classifier: Development Status :: 3 - Alpha
Classifier: Intended Audience :: Developers
Classifier: Topic :: Software Development :: Build Tools
Classifier: License :: OSI Approved :: MIT License
Classifier: Programming Language :: Python :: 3
Classifier: Programming Language :: Python :: 3.6
